qa/__init__.py
qa/app.py
qa/edit_distance.py
qa/parsedata.py
travis_ci_cd-0.0.1.data/data/answers/Answers.txt
travis_ci_cd-0.0.1.data/data/questions/Questions.txt
travis_ci_cd-0.0.1.data/data/topics/Topics.txt
travis_ci_cd-0.0.1.dist-info/METADATA
travis_ci_cd-0.0.1.dist-info/WHEEL
travis_ci_cd-0.0.1.dist-info/entry_points.txt
travis_ci_cd-0.0.1.dist-info/top_level.txt
travis_ci_cd-0.0.1.dist-info/RECORD
