Metadata-Version: 2.1
Name: travis-ci-cd
Version: 0.0.1
Summary: A Python Flask NLP application with CICD in Travis CI
Home-page: https://github.com/topnotchbiz/travis-ci-cd
Author: Yin Jin
Author-email: jin.yin1229@outlook.com
License: UNKNOWN
Keywords: travisci setuptools development
Platform: UNKNOWN
Classifier: Development Status :: 3 - Alpha
Classifier: Intended Audience :: Developers
Classifier: Topic :: Software Development :: Build Tools
Classifier: License :: OSI Approved :: MIT License
Classifier: Programming Language :: Python :: 3.6
Classifier: Programming Language :: Python :: 3.7
Classifier: Programming Language :: Python :: 3.8
Requires-Python: >=2.7, !=3.0.*, !=3.1.*, !=3.2.*, !=3.3.*, !=3.4.*, !=3.5.*, <4
